mcp_ai_hub/__init__.py
mcp_ai_hub/ai_client.py
mcp_ai_hub/config.py
mcp_ai_hub/py.typed
mcp_ai_hub/server.py
mcp_ai_hub-0.1.3.dist-info/METADATA
mcp_ai_hub-0.1.3.dist-info/WHEEL
mcp_ai_hub-0.1.3.dist-info/entry_points.txt
mcp_ai_hub-0.1.3.dist-info/licenses/LICENSE
mcp_ai_hub-0.1.3.dist-info/RECORD
