Metadata-Version: 2.4
Name: mcp-ai-hub
Version: 0.1.3
Summary: A Model Context Protocol (MCP) server that provides unified access to various AI providers through LiteLM. Chat with OpenAI, Anthropic, and 100+ other AI models using a single, consistent interface.
Project-URL: Homepage, https://github.com/feiskyer/mcp-ai-hub
Project-URL: Repository, https://github.com/feiskyer/mcp-ai-hub
Project-URL: Documentation, https://github.com/feiskyer/mcp-ai-hub#readme
Project-URL: Bug Tracker, https://github.com/feiskyer/mcp-ai-hub/issues
Author-email: Pengfei Ni <feiskyer@gmail.com>
License-File: LICENSE
Classifier: Development Status :: 4 - Beta
Classifier: Intended Audience :: Developers
Classifier: License :: OSI Approved :: MIT License
Classifier: Programming Language :: Python :: 3
Classifier: Programming Language :: Python :: 3.10
Classifier: Programming Language :: Python :: 3.11
Classifier: Programming Language :: Python :: 3.12
Classifier: Programming Language :: Python :: 3.13
Classifier: Topic :: Scientific/Engineering :: Artificial Intelligence
Classifier: Topic :: Software Development :: Libraries :: Python Modules
Requires-Python: >=3.10
Requires-Dist: httpx[socks]>=0.25.0
Requires-Dist: litellm>=1.0.0
Requires-Dist: mcp>=1.2.0
Requires-Dist: pydantic>=2.0.0
Requires-Dist: pyyaml>=6.0
Provides-Extra: dev
Requires-Dist: mypy>=1.0.0; extra == 'dev'
Requires-Dist: pre-commit>=3.0.0; extra == 'dev'
Requires-Dist: pytest-asyncio>=0.21.0; extra == 'dev'
Requires-Dist: pytest-cov>=4.0.0; extra == 'dev'
Requires-Dist: pytest>=7.0.0; extra == 'dev'
Requires-Dist: ruff>=0.1.0; extra == 'dev'
Requires-Dist: types-pyyaml>=6.0.0; extra == 'dev'
